mysql_utilities.cpython-310-x86_64-linux-gnu.so
reese_mysql_utils-0.0.2.dist-info/WHEEL
reese_mysql_utils-0.0.2.dist-info/top_level.txt
reese_mysql_utils-0.0.2.dist-info/RECORD
reese_mysql_utils-0.0.2.dist-info/METADATA
